<?xml version="1.0" encoding="utf-8" ?>
<dwsync>
<file name=".csscomb.json" server="dev.novaonidc.vn//public_html/backup/vietthanhpro/" local="130776612410332422" remote="130753806000000000" Dst="0" />
<file name=".csslintrc" server="dev.novaonidc.vn//public_html/backup/vietthanhpro/" local="130776612410382479" remote="130753806000000000" Dst="0" />
<file name="alerts.less" server="dev.novaonidc.vn//public_html/backup/vietthanhpro/" local="130776612410442492" remote="130753806000000000" Dst="0" />
<file name="badges.less" server="dev.novaonidc.vn//public_html/backup/vietthanhpro/" local="130776612413074239" remote="130753806000000000" Dst="0" />
<file name="bootstrap.less" server="dev.novaonidc.vn//public_html/backup/vietthanhpro/" local="130776612413094260" remote="130753806000000000" Dst="0" />
<file name="breadcrumbs.less" server="dev.novaonidc.vn//public_html/backup/vietthanhpro/" local="130776612413144330" remote="130753806000000000" Dst="0" />
<file name="button-groups.less" server="dev.novaonidc.vn//public_html/backup/vietthanhpro/" local="130776612415705987" remote="130753806000000000" Dst="0" />
<file name="buttons.less" server="dev.novaonidc.vn//public_html/backup/vietthanhpro/" local="130776612415916144" remote="130753806000000000" Dst="0" />
<file name="carousel.less" server="dev.novaonidc.vn//public_html/backup/vietthanhpro/" local="130776612416006200" remote="130753806000000000" Dst="0" />
<file name="close.less" server="dev.novaonidc.vn//public_html/backup/vietthanhpro/" local="130776612418437808" remote="130753806000000000" Dst="0" />
<file name="code.less" server="dev.novaonidc.vn//public_html/backup/vietthanhpro/" local="130776612418487865" remote="130753806000000000" Dst="0" />
<file name="component-animations.less" server="dev.novaonidc.vn//public_html/backup/vietthanhpro/" local="130776612418507878" remote="130753806000000000" Dst="0" />
<file name="dropdowns.less" server="dev.novaonidc.vn//public_html/backup/vietthanhpro/" local="130776612421169670" remote="130753806000000000" Dst="0" />
<file name="forms.less" server="dev.novaonidc.vn//public_html/backup/vietthanhpro/" local="130776612421239679" remote="130753806000000000" Dst="0" />
<file name="glyphicons.less" server="dev.novaonidc.vn//public_html/backup/vietthanhpro/" local="130776612421659951" remote="130753806000000000" Dst="0" />
<file name="grid.less" server="dev.novaonidc.vn//public_html/backup/vietthanhpro/" local="130776612423961524" remote="130753806000000000" Dst="0" />
<file name="input-groups.less" server="dev.novaonidc.vn//public_html/backup/vietthanhpro/" local="130776612424011526" remote="130753806000000000" Dst="0" />
<file name="jumbotron.less" server="dev.novaonidc.vn//public_html/backup/vietthanhpro/" local="130776612424061590" remote="130753806000000000" Dst="0" />
<file name="labels.less" server="dev.novaonidc.vn//public_html/backup/vietthanhpro/" local="130776612426513225" remote="130753806000000000" Dst="0" />
<file name="list-group.less" server="dev.novaonidc.vn//public_html/backup/vietthanhpro/" local="130776612426563220" remote="130753806000000000" Dst="0" />
<file name="media.less" server="dev.novaonidc.vn//public_html/backup/vietthanhpro/" local="130776612426623288" remote="130753806000000000" Dst="0" />
<file name="mixins.less" server="dev.novaonidc.vn//public_html/backup/vietthanhpro/" local="130776612453219238" remote="130753806000000000" Dst="0" />
<file name="modals.less" server="dev.novaonidc.vn//public_html/backup/vietthanhpro/" local="130776612455820942" remote="130753806000000000" Dst="0" />
<file name="navbar.less" server="dev.novaonidc.vn//public_html/backup/vietthanhpro/" local="130776612455890985" remote="130753806000000000" Dst="0" />
<file name="navs.less" server="dev.novaonidc.vn//public_html/backup/vietthanhpro/" local="130776612456001096" remote="130753806000000000" Dst="0" />
<file name="normalize.less" server="dev.novaonidc.vn//public_html/backup/vietthanhpro/" local="130776612462995719" remote="130753806000000000" Dst="0" />
<file name="pager.less" server="dev.novaonidc.vn//public_html/backup/vietthanhpro/" local="130776612463045783" remote="130753806000000000" Dst="0" />
<file name="pagination.less" server="dev.novaonidc.vn//public_html/backup/vietthanhpro/" local="130776612463115799" remote="130753806000000000" Dst="0" />
<file name="panels.less" server="dev.novaonidc.vn//public_html/backup/vietthanhpro/" local="130776612466988372" remote="130753806000000000" Dst="0" />
<file name="popovers.less" server="dev.novaonidc.vn//public_html/backup/vietthanhpro/" local="130776612467048439" remote="130753806000000000" Dst="0" />
<file name="print.less" server="dev.novaonidc.vn//public_html/backup/vietthanhpro/" local="130776612467068418" remote="130753806000000000" Dst="0" />
<file name="progress-bars.less" server="dev.novaonidc.vn//public_html/backup/vietthanhpro/" local="130776612469600147" remote="130753806000000000" Dst="0" />
<file name="responsive-embed.less" server="dev.novaonidc.vn//public_html/backup/vietthanhpro/" local="130776612469630157" remote="130753806000000000" Dst="0" />
<file name="responsive-utilities.less" server="dev.novaonidc.vn//public_html/backup/vietthanhpro/" local="130776612469750209" remote="130753806000000000" Dst="0" />
<file name="scaffolding.less" server="dev.novaonidc.vn//public_html/backup/vietthanhpro/" local="130776612472231874" remote="130753806000000000" Dst="0" />
<file name="tables.less" server="dev.novaonidc.vn//public_html/backup/vietthanhpro/" local="130776612472301903" remote="130753806000000000" Dst="0" />
<file name="theme.less" server="dev.novaonidc.vn//public_html/backup/vietthanhpro/" local="130776612472502064" remote="130753806000000000" Dst="0" />
<file name="thumbnails.less" server="dev.novaonidc.vn//public_html/backup/vietthanhpro/" local="130776612474813578" remote="130753806000000000" Dst="0" />
<file name="tooltip.less" server="dev.novaonidc.vn//public_html/backup/vietthanhpro/" local="130776612474863642" remote="130753806000000000" Dst="0" />
<file name="type.less" server="dev.novaonidc.vn//public_html/backup/vietthanhpro/" local="130776612474993691" remote="130753806000000000" Dst="0" />
<file name="utilities.less" server="dev.novaonidc.vn//public_html/backup/vietthanhpro/" local="130776612477515368" remote="130753806000000000" Dst="0" />
<file name="variables.less" server="dev.novaonidc.vn//public_html/backup/vietthanhpro/" local="130776612477635455" remote="130753806000000000" Dst="0" />
<file name="wells.less" server="dev.novaonidc.vn//public_html/backup/vietthanhpro/" local="130776612477695495" remote="130753806000000000" Dst="0" />
</dwsync>