<?xml version="1.0" encoding="utf-8" ?>
<dwsync>
<file name="amazon_checkout.php" server="dev.novaonidc.vn//public_html/backup/vietthanhpro/" local="130776613415590950" remote="130753806000000000" Dst="0" />
<file name="authorizenet_aim.php" server="dev.novaonidc.vn//public_html/backup/vietthanhpro/" local="130776613418032567" remote="130753806000000000" Dst="0" />
<file name="authorizenet_sim.php" server="dev.novaonidc.vn//public_html/backup/vietthanhpro/" local="130776613418052581" remote="130753806000000000" Dst="0" />
<file name="bank_transfer.php" server="dev.novaonidc.vn//public_html/backup/vietthanhpro/" local="130776613418182677" remote="130753806000000000" Dst="0" />
<file name="bluepay_hosted.php" server="dev.novaonidc.vn//public_html/backup/vietthanhpro/" local="130776613420634305" remote="130753806000000000" Dst="0" />
<file name="bluepay_redirect.php" server="dev.novaonidc.vn//public_html/backup/vietthanhpro/" local="130776613420764388" remote="130753806000000000" Dst="0" />
<file name="cheque.php" server="dev.novaonidc.vn//public_html/backup/vietthanhpro/" local="130776613420864448" remote="130753806000000000" Dst="0" />
<file name="cod.php" server="dev.novaonidc.vn//public_html/backup/vietthanhpro/" local="130776613423306079" remote="130753806000000000" Dst="0" />
<file name="firstdata.php" server="dev.novaonidc.vn//public_html/backup/vietthanhpro/" local="130776613423326099" remote="130753806000000000" Dst="0" />
<file name="firstdata_remote.php" server="dev.novaonidc.vn//public_html/backup/vietthanhpro/" local="130776613423476203" remote="130753806000000000" Dst="0" />
<file name="free_checkout.php" server="dev.novaonidc.vn//public_html/backup/vietthanhpro/" local="130776613425927823" remote="130753806000000000" Dst="0" />
<file name="klarna_account.php" server="dev.novaonidc.vn//public_html/backup/vietthanhpro/" local="130776613426067917" remote="130753806000000000" Dst="0" />
<file name="klarna_invoice.php" server="dev.novaonidc.vn//public_html/backup/vietthanhpro/" local="130776613426208017" remote="130753806000000000" Dst="0" />
<file name="liqpay.php" server="dev.novaonidc.vn//public_html/backup/vietthanhpro/" local="130776613428629635" remote="130753806000000000" Dst="0" />
<file name="nochex.php" server="dev.novaonidc.vn//public_html/backup/vietthanhpro/" local="130776613428729687" remote="130753806000000000" Dst="0" />
<file name="paymate.php" server="dev.novaonidc.vn//public_html/backup/vietthanhpro/" local="130776613428839757" remote="130753806000000000" Dst="0" />
<file name="paypoint.php" server="dev.novaonidc.vn//public_html/backup/vietthanhpro/" local="130776613431251365" remote="130753806000000000" Dst="0" />
<file name="payza.php" server="dev.novaonidc.vn//public_html/backup/vietthanhpro/" local="130776613431361435" remote="130753806000000000" Dst="0" />
<file name="perpetual_payments.php" server="dev.novaonidc.vn//public_html/backup/vietthanhpro/" local="130776613431471512" remote="130753806000000000" Dst="0" />
<file name="pp_express.php" server="dev.novaonidc.vn//public_html/backup/vietthanhpro/" local="130776613433953156" remote="130753806000000000" Dst="0" />
<file name="pp_payflow.php" server="dev.novaonidc.vn//public_html/backup/vietthanhpro/" local="130776613434073236" remote="130753806000000000" Dst="0" />
<file name="pp_payflow_iframe.php" server="dev.novaonidc.vn//public_html/backup/vietthanhpro/" local="130776613434083253" remote="130753806000000000" Dst="0" />
<file name="pp_pro.php" server="dev.novaonidc.vn//public_html/backup/vietthanhpro/" local="130776613436644950" remote="130753806000000000" Dst="0" />
<file name="pp_pro_iframe.php" server="dev.novaonidc.vn//public_html/backup/vietthanhpro/" local="130776613436654974" remote="130753806000000000" Dst="0" />
<file name="pp_standard.php" server="dev.novaonidc.vn//public_html/backup/vietthanhpro/" local="130776613436785050" remote="130753806000000000" Dst="0" />
<file name="realex.php" server="dev.novaonidc.vn//public_html/backup/vietthanhpro/" local="130776613439236671" remote="130753806000000000" Dst="0" />
<file name="realex_remote.php" server="dev.novaonidc.vn//public_html/backup/vietthanhpro/" local="130776613439356758" remote="130753806000000000" Dst="0" />
<file name="sagepay_direct.php" server="dev.novaonidc.vn//public_html/backup/vietthanhpro/" local="130776613439476906" remote="130753806000000000" Dst="0" />
<file name="sagepay_server.php" server="dev.novaonidc.vn//public_html/backup/vietthanhpro/" local="130776613441928465" remote="130753806000000000" Dst="0" />
<file name="sagepay_us.php" server="dev.novaonidc.vn//public_html/backup/vietthanhpro/" local="130776613442028552" remote="130753806000000000" Dst="0" />
<file name="securetrading_pp.php" server="dev.novaonidc.vn//public_html/backup/vietthanhpro/" local="130776613442118595" remote="130753806000000000" Dst="0" />
<file name="securetrading_ws.php" server="dev.novaonidc.vn//public_html/backup/vietthanhpro/" local="130776613444500179" remote="130753806000000000" Dst="0" />
<file name="skrill.php" server="dev.novaonidc.vn//public_html/backup/vietthanhpro/" local="130776613445030536" remote="130753806000000000" Dst="0" />
<file name="twocheckout.php" server="dev.novaonidc.vn//public_html/backup/vietthanhpro/" local="130776613445040539" remote="130753806000000000" Dst="0" />
<file name="web_payment_software.php" server="dev.novaonidc.vn//public_html/backup/vietthanhpro/" local="130776613447572220" remote="130753806000000000" Dst="0" />
<file name="worldpay.php" server="dev.novaonidc.vn//public_html/backup/vietthanhpro/" local="130776613447592233" remote="130753806000000000" Dst="0" />
</dwsync>